{
  "packages": [
    {
      "name": "trans_generated_from_words",
      "decks": [
        {
          "id": "581e137a-58f1-4317-bae9-0a99d41f381d",
          "name": "Russian-Armenian auto-translated",
          "src": [
            {
              "type": "autogenerate_am",
              "file": "words.txt",
              "pronunciation_in_reverse": true,
              "one_translation": true,
              "card_color": "#f5f5f5",
              "card_properties": {
                "tags": [
                  "armenian",
                  "russian",
                  "autogenerated"
                ]
              }
            }
          ]
        }
      ]
    }
  ]
}
